{
  "commitID": "4f46b6726efe1937b6edefaf62e6b4a88c534217",
  "fileName": "ST_Agedgeinfo_t.java",
  "packageName": "h",
  "importName": ["smetana.core.__struct__"],
  "classData": {
    "h.ST_Agedgeinfo_t": {
      "type": "CLASS",
      "modifier": ["final", "public"],
      "field": [{
        "name": "spl",
        "type": "h.ST_splines",
        "modifier": ["public"]
      }, {
        "name": "tail_port",
        "type": "h.ST_port",
        "modifier": ["public", "final"]
      }, {
        "name": "head_port",
        "type": "h.ST_port",
        "modifier": ["public", "final"]
      }, {
        "name": "label",
        "type": "h.ST_textlabel_t",
        "modifier": ["public"]
      }, {
        "name": "head_label",
        "type": "h.ST_textlabel_t",
        "modifier": ["public"]
      }, {
        "name": "tail_label",
        "type": "h.ST_textlabel_t",
        "modifier": ["public"]
      }, {
        "name": "xlabel",
        "type": "h.ST_textlabel_t",
        "modifier": ["public"]
      }, {
        "name": "edge_type",
        "type": "int",
        "modifier": ["public"]
      }, {
        "name": "adjacent",
        "type": "int",
        "modifier": ["public"]
      }, {
        "name": "label_ontop",
        "type": "boolean",
        "modifier": ["public"]
      }, {
        "name": "to_orig",
        "type": "h.ST_Agedge_s",
        "modifier": ["public"]
      }, {
        "name": "dist",
        "type": "double",
        "modifier": ["public"]
      }, {
        "name": "showboxes",
        "type": "int",
        "modifier": ["public"]
      }, {
        "name": "conc_opp_flag",
        "type": "boolean",
        "modifier": ["public"]
      }, {
        "name": "xpenalty",
        "type": "int",
        "modifier": ["public"]
      }, {
        "name": "weight",
        "type": "int",
        "modifier": ["public"]
      }, {
        "name": "cutvalue",
        "type": "int",
        "modifier": ["public"]
      }, {
        "name": "tree_index",
        "type": "int",
        "modifier": ["public"]
      }, {
        "name": "count",
        "type": "int",
        "modifier": ["public"]
      }, {
        "name": "minlen",
        "type": "int",
        "modifier": ["public"]
      }, {
        "name": "to_virt",
        "type": "h.ST_Agedge_s",
        "modifier": ["public"]
      }],
      "methodData": {
        "h.ST_Agedgeinfo_t.___#18482274": {
          "returnType": "void",
          "modifier": ["public"],
          "parameter": [{
            "name": "other",
            "type": "smetana.core.__struct__"
          }],
          "annotation": ["java.lang.Override"],
          "metric": {
            "loc": "27",
            "cyclomatic_complexity": "1",
            "nestedBlockDepth": "1"
          }
        }
      },
      "superClass": "h.ST_Agrec_s",
      "metric": {
        "loc": "50",
        "cyclomatic_complexity": "1",
        "cyclomatic_complexity_weighted": "1",
        "LCOM4": "0"
      }
    }
  },
  "metric": {
    "loc": "100",
    "cyclomatic_complexity": "1"
  },
  "author": "plantuml@gmail.com"
}