{
  "commitID": "97aba3f4e6a3619763dcc200d355e064020c0ee8",
  "fileName": "PetTypeEditor.java",
  "packageName": "org.springframework.samples.petclinic.web",
  "importName": ["java.beans.PropertyEditorSupport", "org.springframework.samples.petclinic.PetType", "org.springframework.samples.petclinic.service.ClinicService"],
  "classData": {
    "org.springframework.samples.petclinic.web.PetTypeEditor": {
      "type": "CLASS",
      "modifier": ["public"],
      "field": [{
        "name": "clinicService",
        "type": "org.springframework.samples.petclinic.service.ClinicService",
        "modifier": ["private", "final"]
      }],
      "methodData": {
        "org.springframework.samples.petclinic.web.PetTypeEditor.PetTypeEditor#8a3aa4ac": {
          "modifier": ["public"],
          "parameter": [{
            "name": "clinicService",
            "type": "org.springframework.samples.petclinic.service.ClinicService"
          }],
          "isConstructor": true,
          "metric": {
            "loc": "3",
            "cyclomatic_complexity": "1",
            "nestedBlockDepth": "1"
          }
        },
        "org.springframework.samples.petclinic.web.PetTypeEditor.setAsText#943a4c50": {
          "returnType": "void",
          "modifier": ["public"],
          "parameter": [{
            "name": "text",
            "type": "java.lang.String"
          }],
          "annotation": ["java.lang.Override"],
          "metric": {
            "loc": "8",
            "cyclomatic_complexity": "2",
            "nestedBlockDepth": "3"
          }
        }
      },
      "superClass": "java.beans.PropertyEditorSupport",
      "metric": {
        "loc": "19",
        "cyclomatic_complexity": "2",
        "cyclomatic_complexity_weighted": "2",
        "LCOM4": "0"
      }
    }
  },
  "metric": {
    "loc": "26",
    "cyclomatic_complexity": "2"
  },
  "author": "misvy@vmware.com",
  "modifiedLines": 1
}