{
  "commitID": "0a795acbb355994a00bbe2973a408a5fb873f503",
  "fileName": "Col.java",
  "packageName": "net.sourceforge.plantuml.bpm",
  "classData": {
    "net.sourceforge.plantuml.bpm.Col": {
      "type": "CLASS",
      "modifier": ["public"],
      "metric": {
        "loc": "3",
        "cyclomatic_complexity": "1",
        "cyclomatic_complexity_weighted": "1",
        "LCOM4": "0"
      }
    }
  },
  "metric": {
    "loc": "40",
    "cyclomatic_complexity": "1"
  },
  "author": "dietrich.travkin@solunar.de"
}