{
  "commitID": "b8b98d0c18c4f2e7129b5891c15076145b111cfc",
  "fileName": "CommandMultilinesComment.java",
  "packageName": "net.sourceforge.plantuml.command",
  "importName": ["net.sourceforge.plantuml.core.Diagram", "net.sourceforge.plantuml.utils.BlocLines"],
  "classData": {
    "net.sourceforge.plantuml.command.CommandMultilinesComment": {
      "type": "CLASS",
      "modifier": ["public"],
      "field": [{
        "name": "COMMENT_MULTILINE_START",
        "type": "java.lang.String",
        "modifier": ["public", "static", "final"]
      }, {
        "name": "COMMENT_MULTILINE_END",
        "type": "java.lang.String",
        "modifier": ["public", "static", "final"]
      }, {
        "name": "COMMENT_SINGLE_LINE",
        "type": "java.lang.String",
        "modifier": ["public", "static", "final"]
      }, {
        "name": "INNER_COMMENT",
        "type": "java.lang.String",
        "modifier": ["public", "static", "final"]
      }],
      "methodData": {
        "net.sourceforge.plantuml.command.CommandMultilinesComment.getPatternEnd#1": {
          "returnType": "java.lang.String",
          "modifier": ["public"],
          "annotation": ["java.lang.Override"],
          "metric": {
            "loc": "4",
            "cyclomatic_complexity": "1",
            "nestedBlockDepth": "1"
          }
        },
        "net.sourceforge.plantuml.command.CommandMultilinesComment.execute#9f6c734f": {
          "returnType": "net.sourceforge.plantuml.command.CommandExecutionResult",
          "modifier": ["public"],
          "parameter": [{
            "name": "diagram",
            "type": "net.sourceforge.plantuml.core.Diagram",
            "modifier": ["final "]
          }, {
            "name": "lines",
            "type": "net.sourceforge.plantuml.utils.BlocLines"
          }],
          "metric": {
            "loc": "3",
            "cyclomatic_complexity": "1",
            "nestedBlockDepth": "1"
          }
        },
        "net.sourceforge.plantuml.command.CommandMultilinesComment.CommandMultilinesComment#1": {
          "modifier": ["private"],
          "isConstructor": true,
          "metric": {
            "loc": "3",
            "cyclomatic_complexity": "1",
            "nestedBlockDepth": "1"
          }
        }
      },
      "superClass": "net.sourceforge.plantuml.command.CommandMultilines\u003cnet.sourceforge.plantuml.core.Diagram\u003e",
      "metric": {
        "loc": "21",
        "cyclomatic_complexity": "1",
        "cyclomatic_complexity_weighted": "1",
        "LCOM4": "1"
      }
    }
  },
  "metric": {
    "loc": "61",
    "cyclomatic_complexity": "1"
  },
  "author": "plantuml@gmail.com"
}