{
  "commitID": "b8b98d0c18c4f2e7129b5891c15076145b111cfc",
  "fileName": "MDAPackageImpl.java",
  "packageName": "net.sourceforge.plantuml.mda",
  "importName": ["java.util.ArrayList", "java.util.Collection", "java.util.Collections", "net.sourceforge.plantuml.abel.Entity", "net.sourceforge.plantuml.api.mda.option2.MDAEntity", "net.sourceforge.plantuml.api.mda.option2.MDAPackage"],
  "classData": {
    "net.sourceforge.plantuml.mda.MDAPackageImpl": {
      "type": "CLASS",
      "modifier": ["public"],
      "interface": ["net.sourceforge.plantuml.api.mda.option2.MDAPackage"],
      "field": [{
        "name": "entities",
        "type": "java.util.Collection\u003cnet.sourceforge.plantuml.api.mda.option2.MDAEntity\u003e",
        "modifier": ["private", "final"]
      }, {
        "name": "group",
        "type": "net.sourceforge.plantuml.abel.Entity",
        "modifier": ["private", "final"]
      }],
      "methodData": {
        "net.sourceforge.plantuml.mda.MDAPackageImpl.MDAPackageImpl#7c02d022": {
          "modifier": ["public"],
          "parameter": [{
            "name": "group",
            "type": "net.sourceforge.plantuml.abel.Entity"
          }],
          "isConstructor": true,
          "metric": {
            "loc": "6",
            "cyclomatic_complexity": "1",
            "nestedBlockDepth": "2"
          }
        },
        "net.sourceforge.plantuml.mda.MDAPackageImpl.getName#1": {
          "returnType": "java.lang.String",
          "modifier": ["public"],
          "metric": {
            "loc": "6",
            "cyclomatic_complexity": "1",
            "nestedBlockDepth": "2"
          }
        },
        "net.sourceforge.plantuml.mda.MDAPackageImpl.getEntities#1": {
          "returnType": "java.util.Collection\u003cnet.sourceforge.plantuml.api.mda.option2.MDAEntity\u003e",
          "modifier": ["public"],
          "metric": {
            "loc": "3",
            "cyclomatic_complexity": "1",
            "nestedBlockDepth": "1"
          }
        }
      },
      "metric": {
        "loc": "24",
        "cyclomatic_complexity": "2",
        "cyclomatic_complexity_weighted": "1",
        "LCOM4": "2"
      }
    }
  },
  "metric": {
    "loc": "69",
    "cyclomatic_complexity": "1"
  },
  "author": "plantuml@gmail.com"
}