{
  "commitID": "b8b98d0c18c4f2e7129b5891c15076145b111cfc",
  "fileName": "ResetFont.java",
  "packageName": "net.sourceforge.plantuml.klimt.creole.command",
  "importName": ["net.sourceforge.plantuml.klimt.font.FontConfiguration"],
  "classData": {
    "net.sourceforge.plantuml.klimt.creole.command.ResetFont": {
      "type": "CLASS",
      "interface": ["net.sourceforge.plantuml.klimt.creole.command.FontChange"],
      "methodData": {
        "net.sourceforge.plantuml.klimt.creole.command.ResetFont.apply#744b90e6": {
          "returnType": "net.sourceforge.plantuml.klimt.font.FontConfiguration",
          "modifier": ["public"],
          "parameter": [{
            "name": "initial",
            "type": "net.sourceforge.plantuml.klimt.font.FontConfiguration"
          }],
          "metric": {
            "loc": "3",
            "cyclomatic_complexity": "1",
            "nestedBlockDepth": "1"
          }
        }
      },
      "metric": {
        "loc": "7",
        "cyclomatic_complexity": "1",
        "cyclomatic_complexity_weighted": "1",
        "LCOM4": "1"
      }
    }
  },
  "metric": {
    "loc": "46",
    "cyclomatic_complexity": "1"
  },
  "author": "plantuml@gmail.com"
}