{
  "commitID": "0a795acbb355994a00bbe2973a408a5fb873f503",
  "fileName": "TextLink.java",
  "packageName": "net.sourceforge.plantuml.klimt.creole.command",
  "importName": ["java.util.Objects", "net.sourceforge.plantuml.url.Url"],
  "classData": {
    "net.sourceforge.plantuml.klimt.creole.command.TextLink": {
      "type": "CLASS",
      "modifier": ["public"],
      "interface": ["net.sourceforge.plantuml.klimt.creole.command.HtmlCommand"],
      "field": [{
        "name": "url",
        "type": "net.sourceforge.plantuml.url.Url",
        "modifier": ["private", "final"]
      }],
      "methodData": {
        "net.sourceforge.plantuml.klimt.creole.command.TextLink.getUrl#1": {
          "returnType": "net.sourceforge.plantuml.url.Url",
          "modifier": ["public"],
          "metric": {
            "loc": "3",
            "cyclomatic_complexity": "1",
            "nestedBlockDepth": "1"
          }
        },
        "net.sourceforge.plantuml.klimt.creole.command.TextLink.getText#1": {
          "returnType": "java.lang.String",
          "modifier": ["public"],
          "metric": {
            "loc": "3",
            "cyclomatic_complexity": "1",
            "nestedBlockDepth": "1"
          }
        },
        "net.sourceforge.plantuml.klimt.creole.command.TextLink.TextLink#14d6e": {
          "parameter": [{
            "name": "url",
            "type": "net.sourceforge.plantuml.url.Url"
          }],
          "isConstructor": true,
          "metric": {
            "loc": "3",
            "cyclomatic_complexity": "1",
            "nestedBlockDepth": "1"
          }
        }
      },
      "metric": {
        "loc": "17",
        "cyclomatic_complexity": "1",
        "cyclomatic_complexity_weighted": "1",
        "LCOM4": "1"
      }
    }
  },
  "metric": {
    "loc": "58",
    "cyclomatic_complexity": "1"
  },
  "author": "dietrich.travkin@solunar.de"
}